{"name": "whereto", "version_dict": {"version": "0.4.0", "eq_version": "", "ge_version": "0.4.0", "lt_version": "", "ne_version": []}, "deep": {"count": 1, "list": ["python-openstackclient", "whereto"]}, "requires": {"pbr": {"eq_version": "", "ge_version": "2.0", "lt_version": "", "ne_version": [], "version": "2.0"}, "python-pcre": {"eq_version": "", "ge_version": "", "lt_version": "", "ne_version": [], "version": "unknown"}, "hacking": {"eq_version": "", "ge_version": "0.12.0", "lt_version": "0.13", "ne_version": [], "version": "0.12.0"}, "coverage": {"eq_version": "", "ge_version": "4.0", "lt_version": "", "ne_version": ["4.4"], "version": "4.0"}, "python-subunit": {"eq_version": "", "ge_version": "0.0.18", "lt_version": "", "ne_version": [], "version": "0.0.18"}, "Sphinx": {"eq_version": "", "ge_version": "1.6.2", "lt_version": "", "ne_version": [], "version": "1.6.2"}, "oslotest": {"eq_version": "", "ge_version": "1.10.0", "lt_version": "", "ne_version": [], "version": "1.10.0"}, "testrepository": {"eq_version": "", "ge_version": "0.0.18", "lt_version": "", "ne_version": [], "version": "0.0.18"}, "testtools": {"eq_version": "", "ge_version": "1.4.0", "lt_version": "", "ne_version": [], "version": "1.4.0"}, "openstackdocstheme": {"eq_version": "", "ge_version": "1.17.0", "lt_version": "", "ne_version": [], "version": "1.17.0"}, "reno": {"eq_version": "", "ge_version": "1.8.0", "lt_version": "", "ne_version": [], "version": "1.8.0"}, "sphinxcontrib.autoprogram": {"eq_version": "", "ge_version": "", "lt_version": "", "ne_version": [], "version": "unknown"}}}