{"name": "cotyledon", "version_dict": {"version": "1.7.3", "eq_version": "", "ge_version": "", "lt_version": "", "ne_version": [], "upper_version": "1.7.3"}, "deep": {"count": 1, "list": ["aodh", "cotyledon"]}, "requires": {"setproctitle": {"eq_version": "", "ge_version": "", "lt_version": "", "ne_version": [], "upper_version": "1.1.10", "version": "1.1.10"}, "sphinx-rtd-theme": {"eq_version": "", "ge_version": "", "lt_version": "", "ne_version": [], "upper_version": "", "version": "unknown"}, "Sphinx": {"eq_version": "", "ge_version": "", "lt_version": "", "ne_version": [], "upper_version": "2.2.0", "version": "2.2.0"}, "oslo.config": {"eq_version": "", "ge_version": "3.14.0", "lt_version": "", "ne_version": [], "upper_version": "6.11.3", "version": "6.11.3"}, "mock": {"eq_version": "", "ge_version": "", "lt_version": "", "ne_version": [], "upper_version": "3.0.5", "version": "3.0.5"}, "pytest": {"eq_version": "", "ge_version": "", "lt_version": "", "ne_version": [], "upper_version": "5.1.2", "version": "5.1.2"}, "pytest-cov": {"eq_version": "", "ge_version": "", "lt_version": "", "ne_version": [], "upper_version": "", "version": "unknown"}, "pytest-xdist": {"eq_version": "", "ge_version": "", "lt_version": "", "ne_version": [], "upper_version": "", "version": "unknown"}}}